oprattr/__init__.py
oprattr/_abstract.py
oprattr/_attribute.py
oprattr/_exceptions.py
oprattr/_operand.py
oprattr/_operand.pyi
oprattr/_operations.py
oprattr/_typeface.py
oprattr/_typeface.pyi
oprattr/methods.py
oprattr/mixins.py
oprattr/py.typed
oprattr-0.9.0.dist-info/METADATA
oprattr-0.9.0.dist-info/WHEEL
oprattr-0.9.0.dist-info/licenses/LICENSE
oprattr-0.9.0.dist-info/RECORD
