Metadata-Version: 2.4
Name: oprattr
Version: 0.9.0
Summary: Add your description here
Author-email: Matthew Young <myoung.space.science@gmail.com>
License-File: LICENSE
Requires-Python: >=3.10
Requires-Dist: numerical
Requires-Dist: numpy>=2.2.1
Requires-Dist: scipy>=1.15.0
